{
  "num_optional_cols": 2,
  "disable_progress_bar_animation": false,
  "program_name": "Widget Demo",
  "monospace_display": false,
  "language_dir": "F:\\Dropbox\\pretty_gui\\Gooey\\gooey\\languages",
  "auto_start": false,
  "target": "\"F:\\Dropbox\\pretty_gui\\Gooey\\venv\\Scripts\\python.exe\" -u \"F:/Dropbox/pretty_gui/Gooey/gooey/examples/widget_demo.py\"",
  "widgets": {
    "primary": {
      "command": null,
      "contents": [
        {
          "data": {
            "default": null,
            "choices": [],
            "nargs": "",
            "commands": [],
            "help": "Name of the file you want to process",
            "display_name": "FileChooser"
          },
          "type": "FileChooser",
          "required": true
        },
        {
          "data": {
            "default": null,
            "choices": [],
            "nargs": "",
            "commands": [],
            "help": "Name of the file you want to process",
            "display_name": "DirectoryChooser"
          },
          "type": "DirChooser",
          "required": true
        },
        {
          "data": {
            "default": null,
            "choices": [],
            "nargs": "",
            "commands": [
              "-j",
              "--jaws"
            ],
            "help": "ooop",
            "display_name": "jaws"
          },
          "type": "MultiFileChooser",
          "required": false
        },
        {
          "data": {
            "default": 2,
            "choices": [],
            "nargs": "",
            "commands": [
              "-d",
              "--duration"
            ],
            "help": "Duration (in seconds) of the program output",
            "display_name": "duration"
          },
          "type": "TextField",
          "required": false
        },
        {
          "data": {
            "default": "I'm on \na new line",
            "choices": [],
            "nargs": "",
            "commands": [
              "-u",
              "--textarea"
            ],
            "help": "A multiline textarea",
            "display_name": "textarea"
          },
          "type": "Textarea",
          "required": false
        },
        {
          "data": {
            "default": null,
            "choices": [],
            "nargs": "",
            "commands": [
              "-s",
              "--cron-schedule"
            ],
            "help": "datetime when the cron should begin",
            "display_name": "cron_schedule"
          },
          "type": "DateChooser",
          "required": false
        },
        {
          "data": {
            "default": false,
            "choices": [],
            "nargs": "",
            "commands": [
              "-c",
              "--showtime"
            ],
            "help": "display the countdown timer",
            "display_name": "showtime"
          },
          "type": "CheckBox",
          "required": false
        },
        {
          "data": {
            "default": false,
            "choices": [],
            "nargs": "",
            "commands": [
              "-p",
              "--pause"
            ],
            "help": "Pause execution",
            "display_name": "pause"
          },
          "type": "CheckBox",
          "required": false
        },
        {
          "data": {
            "default": null,
            "choices": [
              "1",
              "2",
              "3",
              "4",
              "5",
              "6",
              "7",
              "8",
              "9",
              "10"
            ],
            "nargs": "",
            "commands": [
              "-v",
              "--verbose"
            ],
            "help": null,
            "display_name": "verbose"
          },
          "type": "Counter",
          "required": false
        },
        {
          "data": {
            "default": true,
            "choices": [],
            "nargs": "",
            "commands": [
              "-o",
              "--overwrite"
            ],
            "help": "Overwrite output file (if present)",
            "display_name": "overwrite"
          },
          "type": "CheckBox",
          "required": false
        },
        {
          "data": {
            "default": null,
            "choices": [
              "yes",
              "no"
            ],
            "nargs": "",
            "commands": [
              "-r",
              "--recursive"
            ],
            "help": "Recurse into subfolders",
            "display_name": "recursive"
          },
          "type": "Dropdown",
          "required": false
        },
        {
          "data": {
            "default": "writelogs",
            "choices": [],
            "nargs": "",
            "commands": [
              "-w",
              "--writelog"
            ],
            "help": "Dump output to local file",
            "display_name": "writelog"
          },
          "type": "TextField",
          "required": false
        },
        {
          "data": {
            "default": false,
            "choices": [],
            "nargs": "",
            "commands": [
              "-e",
              "--error"
            ],
            "help": "Stop process on error (default: No)",
            "display_name": "error"
          },
          "type": "CheckBox",
          "required": false
        },
        {
          "data": [
            {
              "help": "Show more details",
              "nargs": "",
              "commands": [
                "-t",
                "--verbozze"
              ],
              "choices": null,
              "display_name": "verbose"
            },
            {
              "help": "Only output on error",
              "nargs": "",
              "commands": [
                "-q",
                "--quiet"
              ],
              "choices": null,
              "display_name": "quiet"
            }
          ],
          "type": "RadioGroup",
          "group_name": "Choose Option",
          "required": false
        }
      ]
    }
  },
  "default_size": [
    610,
    530
  ],
  "layout_type": "standard",
  "progress_regex": null,
  "num_required_cols": 1,
  "image_dir": "default",
  "show_advanced": true,
  "disable_stop_button": false,
  "program_description": "Example application to show Gooey's various widgets BROOOOO",
  "manual_start": false,
  "progress_expr": null,
  "language": "english",
  "group_by_type": false
}